pnet/Script_Brain_Template.py
pnet/__init__.py
pnet/Basic/Brain_Template.py
pnet/Basic/Cluster_Computation.py
pnet/Basic/Computation_Environment.py
pnet/Basic/Cropping.py
pnet/Basic/Matrix_Computation.py
pnet/Basic/__init__.py
pnet/Brain_Template/FreeSurfer_fsaverage5/Brain_Template.json.zip
pnet/Brain_Template/FreeSurfer_fsaverage5/Brain_Template.log
pnet/Brain_Template/FreeSurfer_fsaverage5/Brain_Template.mat
pnet/Brain_Template/HCP_Surface/Brain_Template.json.zip
pnet/Brain_Template/HCP_Surface/Brain_Template.log
pnet/Brain_Template/HCP_Surface/Brain_Template.mat
pnet/Brain_Template/HCP_Surface_Volume/Brain_Template.json.zip
pnet/Brain_Template/HCP_Surface_Volume/Brain_Template.log
pnet/Brain_Template/HCP_Surface_Volume/Brain_Template.mat
pnet/Brain_Template/HCP_Surface_Volume/CIFTI_Volume.nii.gz
pnet/Brain_Template/HCP_Surface_Volume/Log_Brain_Template.log
pnet/Brain_Template/HCP_Surface_Volume/T1.nii.gz
pnet/Brain_Template/HCP_Volume/Brain_Template.json.zip
pnet/Brain_Template/HCP_Volume/Brain_Template.log
pnet/Brain_Template/HCP_Volume/Brain_Template.mat
pnet/Brain_Template/MNI_Volume/Brain_Mask.mat
pnet/Brain_Template/MNI_Volume/Brain_Template.json.zip
pnet/Brain_Template/MNI_Volume/Brain_Template.log
pnet/Brain_Template/MNI_Volume/Brain_Template.mat
pnet/Brain_Template/MNI_Volume/Log_Brain_Template.log
pnet/Brain_Template/MNI_Volume/Overlay_Image.mat
pnet/Color/Color_Table.mat
pnet/Module/Data_Input.py
pnet/Module/FN_Computation.py
pnet/Module/FN_Computation_torch.py
pnet/Module/GIG_ICA.py
pnet/Module/Quality_Control.py
pnet/Module/Quality_Control_torch.py
pnet/Module/SR_NMF.py
pnet/Module/Visualization.py
pnet/Module/__init__.py
pnet/Report/Web_Report.py
pnet/Report/Web_Template_Individual.html
pnet/Report/Web_Template_Summary.html
pnet/Report/__init__.py
pnet/Workflow/Workflow_Cluster_Template.py
pnet/Workflow/Workflow_Func.py
pnet/Workflow/Workflow_guide.py
pnet/Workflow/__init__.py
fmripnet-1.0.1.dist-info/METADATA
fmripnet-1.0.1.dist-info/WHEEL
fmripnet-1.0.1.dist-info/top_level.txt
fmripnet-1.0.1.dist-info/RECORD
