Metadata-Version: 2.1
Name: fmripnet
Version: 1.0.1
Summary: pNet: a python package for computing personalized fucntional networks
Home-page: https://github.com/MLDataAnalytics/pNet
Classifier: Programming Language :: Python :: 3
Classifier: Operating System :: OS Independent
Requires-Dist: ggplot
Requires-Dist: matplotlib
Requires-Dist: plotnine
Requires-Dist: statsmodels
Requires-Dist: surfplot
